tellus_api_client/__init__.py
tellus_api_client/main.py
tellus_api_client-0.0.6.dist-info/LICENSE
tellus_api_client-0.0.6.dist-info/METADATA
tellus_api_client-0.0.6.dist-info/WHEEL
tellus_api_client-0.0.6.dist-info/top_level.txt
tellus_api_client-0.0.6.dist-info/RECORD
