Metadata-Version: 2.1
Name: tellus-api-client
Version: 0.0.6
Summary: Unofficial Tellus API Client
Home-page: https://github.com/regonn/tellus-api-client
Author: regonn
Author-email: programmer@haizine.art
License: MIT
Project-URL: Bug Reports, https://github.com/regonn/tellus-api-client/issues
Project-URL: Source, https://github.com/regonn/tellus-api-client
Keywords: Tellus,API
Platform: UNKNOWN
Classifier: Development Status :: 1 - Planning
Classifier: License :: OSI Approved :: MIT License
Classifier: Programming Language :: Python
Classifier: Programming Language :: Python :: 3
Classifier: Programming Language :: Python :: 3.7
Classifier: Topic :: Software Development :: Libraries :: Python Modules
Classifier: Framework :: Jupyter
Requires-Python: ~=3.7
Requires-Dist: scikit-image (==0.15.0)
Requires-Dist: requests (==2.22.0)
